[{"id":"64884","name":"Alamudunskiy Rayon","state_id":1004,"state_code":"C","country_id":118,"country_code":"KG","latitude":"42.81985000","longitude":"74.59398000"},{"id":"64890","name":"Belovodskoye","state_id":1004,"state_code":"C","country_id":118,"country_code":"KG","latitude":"42.82944000","longitude":"74.10830000"},{"id":"64894","name":"Chuyskiy Rayon","state_id":1004,"state_code":"C","country_id":118,"country_code":"KG","latitude":"42.66667000","longitude":"75.33333000"},{"id":"64898","name":"Ivanovka","state_id":1004,"state_code":"C","country_id":118,"country_code":"KG","latitude":"42.88778000","longitude":"75.08500000"},{"id":"64902","name":"Kaindy","state_id":1004,"state_code":"C","country_id":118,"country_code":"KG","latitude":"42.82469000","longitude":"73.67585000"},{"id":"64903","name":"Kant","state_id":1004,"state_code":"C","country_id":118,"country_code":"KG","latitude":"42.89106000","longitude":"74.85077000"},{"id":"64906","name":"Kara-Balta","state_id":1004,"state_code":"C","country_id":118,"country_code":"KG","latitude":"42.81423000","longitude":"73.84813000"},{"id":"64911","name":"Kemin","state_id":1004,"state_code":"C","country_id":118,"country_code":"KG","latitude":"42.78611000","longitude":"75.69167000"},{"id":"64917","name":"Lebedinovka","state_id":1004,"state_code":"C","country_id":118,"country_code":"KG","latitude":"42.88454000","longitude":"74.67819000"},{"id":"64921","name":"Sokulukskiy Rayon","state_id":1004,"state_code":"C","country_id":118,"country_code":"KG","latitude":"42.83333000","longitude":"74.33333000"},{"id":"64922","name":"Sosnovka","state_id":1004,"state_code":"C","country_id":118,"country_code":"KG","latitude":"42.63707000","longitude":"73.89608000"},{"id":"64928","name":"Tokmok","state_id":1004,"state_code":"C","country_id":118,"country_code":"KG","latitude":"42.84194000","longitude":"75.30149000"},{"id":"64934","name":"Ysyk-Ata","state_id":1004,"state_code":"C","country_id":118,"country_code":"KG","latitude":"42.72665000","longitude":"75.07444000"}]