[{"id":"104940","name":"Ad Darbasiyah","state_id":2941,"state_code":"HA","country_id":215,"country_code":"SY","latitude":"37.07279000","longitude":"40.65199000"},{"id":"104957","name":"Al \u1e28asakah","state_id":2941,"state_code":"HA","country_id":215,"country_code":"SY","latitude":"36.50237000","longitude":"40.74772000"},{"id":"104950","name":"Al Malikiyah","state_id":2941,"state_code":"HA","country_id":215,"country_code":"SY","latitude":"37.17701000","longitude":"42.14006000"},{"id":"104955","name":"Al Qamishli","state_id":2941,"state_code":"HA","country_id":215,"country_code":"SY","latitude":"37.05215000","longitude":"41.23142000"},{"id":"104960","name":"Al-Malikiyah District","state_id":2941,"state_code":"HA","country_id":215,"country_code":"SY","latitude":"36.94113000","longitude":"41.90157000"},{"id":"104967","name":"Amude","state_id":2941,"state_code":"HA","country_id":215,"country_code":"SY","latitude":"37.10417000","longitude":"40.93000000"}]