[{"id":181,"name":"Baringo County","country_id":113,"country_code":"KE","state_code":"01"},{"id":210,"name":"Bomet County","country_id":113,"country_code":"KE","state_code":"02"},{"id":168,"name":"Bungoma County","country_id":113,"country_code":"KE","state_code":"03"},{"id":161,"name":"Busia County","country_id":113,"country_code":"KE","state_code":"04"},{"id":160,"name":"Central Province","country_id":113,"country_code":"KE","state_code":"200"},{"id":172,"name":"Coast Province","country_id":113,"country_code":"KE","state_code":"300"},{"id":189,"name":"Eastern Province","country_id":113,"country_code":"KE","state_code":"400"},{"id":201,"name":"Elgeyo-Marakwet County","country_id":113,"country_code":"KE","state_code":"05"},{"id":163,"name":"Embu County","country_id":113,"country_code":"KE","state_code":"06"},{"id":196,"name":"Garissa County","country_id":113,"country_code":"KE","state_code":"07"},{"id":195,"name":"Homa Bay County","country_id":113,"country_code":"KE","state_code":"08"},{"id":170,"name":"Isiolo County","country_id":113,"country_code":"KE","state_code":"09"},{"id":197,"name":"Kajiado County","country_id":113,"country_code":"KE","state_code":"10"},{"id":158,"name":"Kakamega County","country_id":113,"country_code":"KE","state_code":"11"},{"id":193,"name":"Kericho County","country_id":113,"country_code":"KE","state_code":"12"},{"id":199,"name":"Kiambu County","country_id":113,"country_code":"KE","state_code":"13"},{"id":174,"name":"Kilifi County","country_id":113,"country_code":"KE","state_code":"14"},{"id":167,"name":"Kirinyaga County","country_id":113,"country_code":"KE","state_code":"15"},{"id":159,"name":"Kisii County","country_id":113,"country_code":"KE","state_code":"16"},{"id":171,"name":"Kisumu County","country_id":113,"country_code":"KE","state_code":"17"},{"id":211,"name":"Kitui County","country_id":113,"country_code":"KE","state_code":"18"},{"id":173,"name":"Kwale County","country_id":113,"country_code":"KE","state_code":"19"},{"id":164,"name":"Laikipia County","country_id":113,"country_code":"KE","state_code":"20"},{"id":166,"name":"Lamu County","country_id":113,"country_code":"KE","state_code":"21"},{"id":184,"name":"Machakos County","country_id":113,"country_code":"KE","state_code":"22"},{"id":188,"name":"Makueni County","country_id":113,"country_code":"KE","state_code":"23"},{"id":187,"name":"Mandera County","country_id":113,"country_code":"KE","state_code":"24"},{"id":194,"name":"Marsabit County","country_id":113,"country_code":"KE","state_code":"25"},{"id":198,"name":"Meru County","country_id":113,"country_code":"KE","state_code":"26"},{"id":190,"name":"Migori County","country_id":113,"country_code":"KE","state_code":"27"},{"id":200,"name":"Mombasa County","country_id":113,"country_code":"KE","state_code":"28"},{"id":178,"name":"Muranga County","country_id":113,"country_code":"KE","state_code":"29"},{"id":191,"name":"Nairobi","country_id":113,"country_code":"KE","state_code":"110"},{"id":203,"name":"Nakuru District","country_id":113,"country_code":"KE","state_code":"31"},{"id":165,"name":"Nandi District","country_id":113,"country_code":"KE","state_code":"32"},{"id":175,"name":"Narok County","country_id":113,"country_code":"KE","state_code":"33"},{"id":162,"name":"North Eastern Province","country_id":113,"country_code":"KE","state_code":"500"},{"id":209,"name":"Nyamira District","country_id":113,"country_code":"KE","state_code":"34"},{"id":192,"name":"Nyandarua County","country_id":113,"country_code":"KE","state_code":"35"},{"id":204,"name":"Nyanza Province","country_id":113,"country_code":"KE","state_code":"600"},{"id":180,"name":"Nyeri County","country_id":113,"country_code":"KE","state_code":"36"},{"id":179,"name":"Rift Valley Province","country_id":113,"country_code":"KE","state_code":"700"},{"id":207,"name":"Samburu County","country_id":113,"country_code":"KE","state_code":"37"},{"id":186,"name":"Siaya County","country_id":113,"country_code":"KE","state_code":"38"},{"id":176,"name":"Taita\u2013Taveta County","country_id":113,"country_code":"KE","state_code":"39"},{"id":205,"name":"Tana River County","country_id":113,"country_code":"KE","state_code":"40"},{"id":185,"name":"Tharaka Nithi County","country_id":113,"country_code":"KE","state_code":"41"},{"id":183,"name":"Trans-Nzoia District","country_id":113,"country_code":"KE","state_code":"42"},{"id":206,"name":"Turkana County","country_id":113,"country_code":"KE","state_code":"43"},{"id":169,"name":"Uasin Gishu District","country_id":113,"country_code":"KE","state_code":"44"},{"id":202,"name":"Vihiga District","country_id":113,"country_code":"KE","state_code":"45"},{"id":182,"name":"Wajir County","country_id":113,"country_code":"KE","state_code":"46"},{"id":208,"name":"West Pokot County","country_id":113,"country_code":"KE","state_code":"47"},{"id":177,"name":"Western Province","country_id":113,"country_code":"KE","state_code":"800"}]