[{"id":2951,"name":"Antananarivo Province","country_id":130,"country_code":"MG","state_code":"T"},{"id":2950,"name":"Antsiranana Province","country_id":130,"country_code":"MG","state_code":"D"},{"id":2948,"name":"Fianarantsoa Province","country_id":130,"country_code":"MG","state_code":"F"},{"id":2953,"name":"Mahajanga Province","country_id":130,"country_code":"MG","state_code":"M"},{"id":2952,"name":"Toamasina Province","country_id":130,"country_code":"MG","state_code":"A"},{"id":2949,"name":"Toliara Province","country_id":130,"country_code":"MG","state_code":"U"}]