[{"id":2594,"name":"Addu Atoll","country_id":133,"country_code":"MV","state_code":"01"},{"id":2587,"name":"Alif Alif Atoll","country_id":133,"country_code":"MV","state_code":"02"},{"id":2600,"name":"Alif Dhaal Atoll","country_id":133,"country_code":"MV","state_code":"00"},{"id":2604,"name":"Central Province","country_id":133,"country_code":"MV","state_code":"CE"},{"id":2590,"name":"Dhaalu Atoll","country_id":133,"country_code":"MV","state_code":"17"},{"id":2599,"name":"Faafu Atoll","country_id":133,"country_code":"MV","state_code":"14"},{"id":2598,"name":"Gaafu Alif Atoll","country_id":133,"country_code":"MV","state_code":"27"},{"id":2603,"name":"Gaafu Dhaalu Atoll","country_id":133,"country_code":"MV","state_code":"28"},{"id":2595,"name":"Gnaviyani Atoll","country_id":133,"country_code":"MV","state_code":"29"},{"id":2586,"name":"Haa Alif Atoll","country_id":133,"country_code":"MV","state_code":"07"},{"id":2597,"name":"Haa Dhaalu Atoll","country_id":133,"country_code":"MV","state_code":"23"},{"id":2596,"name":"Kaafu Atoll","country_id":133,"country_code":"MV","state_code":"26"},{"id":2601,"name":"Laamu Atoll","country_id":133,"country_code":"MV","state_code":"05"},{"id":2607,"name":"Lhaviyani Atoll","country_id":133,"country_code":"MV","state_code":"03"},{"id":2609,"name":"Mal\u00e9","country_id":133,"country_code":"MV","state_code":"MLE"},{"id":2608,"name":"Meemu Atoll","country_id":133,"country_code":"MV","state_code":"12"},{"id":2592,"name":"Noonu Atoll","country_id":133,"country_code":"MV","state_code":"25"},{"id":2589,"name":"North Central Province","country_id":133,"country_code":"MV","state_code":"NC"},{"id":2588,"name":"North Province","country_id":133,"country_code":"MV","state_code":"NO"},{"id":2602,"name":"Raa Atoll","country_id":133,"country_code":"MV","state_code":"13"},{"id":2585,"name":"Shaviyani Atoll","country_id":133,"country_code":"MV","state_code":"24"},{"id":2606,"name":"South Central Province","country_id":133,"country_code":"MV","state_code":"SC"},{"id":2605,"name":"South Province","country_id":133,"country_code":"MV","state_code":"SU"},{"id":2591,"name":"Thaa Atoll","country_id":133,"country_code":"MV","state_code":"08"},{"id":2593,"name":"Upper South Province","country_id":133,"country_code":"MV","state_code":"US"},{"id":2584,"name":"Vaavu Atoll","country_id":133,"country_code":"MV","state_code":"04"}]