[{"id":"9816","name":"Bandar Seri Begawan","state_id":1216,"state_code":"BM","country_id":33,"country_code":"BN","latitude":"4.89035000","longitude":"114.94006000"},{"id":"9818","name":"Berakas A","state_id":1216,"state_code":"BM","country_id":33,"country_code":"BN","latitude":"4.97032000","longitude":"114.92989000"},{"id":"9819","name":"Kapok","state_id":1216,"state_code":"BM","country_id":33,"country_code":"BN","latitude":"5.02447000","longitude":"115.04664000"},{"id":"9821","name":"Mentiri","state_id":1216,"state_code":"BM","country_id":33,"country_code":"BN","latitude":"4.97058000","longitude":"115.02078000"},{"id":"9822","name":"Serasa","state_id":1216,"state_code":"BM","country_id":33,"country_code":"BN","latitude":"5.01718000","longitude":"115.05841000"}]