[{"id":"107145","name":"Altinova","state_id":2218,"state_code":"77","country_id":225,"country_code":"TR","latitude":"40.69495000","longitude":"29.50986000"},{"id":"107146","name":"Altinova Il\u00e7esi","state_id":2218,"state_code":"77","country_id":225,"country_code":"TR","latitude":"40.70478000","longitude":"29.51606000"},{"id":"107187","name":"Armutlu Il\u00e7esi","state_id":2218,"state_code":"77","country_id":225,"country_code":"TR","latitude":"40.52919000","longitude":"28.83871000"},{"id":"108856","name":"\u00c7inarcik","state_id":2218,"state_code":"77","country_id":225,"country_code":"TR","latitude":"40.64538000","longitude":"29.12450000"},{"id":"108857","name":"\u00c7inarcik Il\u00e7esi","state_id":2218,"state_code":"77","country_id":225,"country_code":"TR","latitude":"40.63669000","longitude":"29.13881000"},{"id":"108831","name":"\u00c7iftlikk\u00f6y","state_id":2218,"state_code":"77","country_id":225,"country_code":"TR","latitude":"40.66028000","longitude":"29.32361000"},{"id":"108832","name":"\u00c7iftlikk\u00f6y Il\u00e7esi","state_id":2218,"state_code":"77","country_id":225,"country_code":"TR","latitude":"40.65302000","longitude":"29.33946000"},{"id":"107862","name":"Kadik\u00f6y","state_id":2218,"state_code":"77","country_id":225,"country_code":"TR","latitude":"40.62015000","longitude":"29.22536000"},{"id":"107955","name":"Kaytazdere","state_id":2218,"state_code":"77","country_id":225,"country_code":"TR","latitude":"40.68225000","longitude":"29.53236000"},{"id":"108099","name":"Kili\u00e7","state_id":2218,"state_code":"77","country_id":225,"country_code":"TR","latitude":"40.63306000","longitude":"29.39472000"},{"id":"108006","name":"Kocadere","state_id":2218,"state_code":"77","country_id":225,"country_code":"TR","latitude":"40.63000000","longitude":"29.03000000"},{"id":"108026","name":"Koruk\u00f6y","state_id":2218,"state_code":"77","country_id":225,"country_code":"TR","latitude":"40.65435000","longitude":"29.16289000"},{"id":"108549","name":"Task\u00f6pr\u00fc","state_id":2218,"state_code":"77","country_id":225,"country_code":"TR","latitude":"40.67361000","longitude":"29.39111000"},{"id":"108572","name":"Termal Il\u00e7esi","state_id":2218,"state_code":"77","country_id":225,"country_code":"TR","latitude":"40.61381000","longitude":"29.18049000"},{"id":"108665","name":"Yalova","state_id":2218,"state_code":"77","country_id":225,"country_code":"TR","latitude":"40.65501000","longitude":"29.27693000"}]