[{"id":"20495","name":"Aguazul","state_id":2892,"state_code":"CAS","country_id":48,"country_code":"CO","latitude":"5.17282000","longitude":"-72.54706000"},{"id":"20677","name":"Chameza","state_id":2892,"state_code":"CAS","country_id":48,"country_code":"CO","latitude":"5.19237000","longitude":"-72.88952000"},{"id":"20704","name":"Ch\u00e1meza","state_id":2892,"state_code":"CAS","country_id":48,"country_code":"CO","latitude":"5.21421000","longitude":"-72.86948000"},{"id":"20937","name":"Hato Corozal","state_id":2892,"state_code":"CAS","country_id":48,"country_code":"CO","latitude":"6.16278000","longitude":"-70.99694000"},{"id":"21062","name":"Man\u00ed","state_id":2892,"state_code":"CAS","country_id":48,"country_code":"CO","latitude":"4.81638000","longitude":"-72.27946000"},{"id":"21101","name":"Monterrey","state_id":2892,"state_code":"CAS","country_id":48,"country_code":"CO","latitude":"4.82015000","longitude":"-72.87901000"},{"id":"21113","name":"Municipio Hato Corozal","state_id":2892,"state_code":"CAS","country_id":48,"country_code":"CO","latitude":"6.15676000","longitude":"-71.76372000"},{"id":"21141","name":"Nunch\u00eda","state_id":2892,"state_code":"CAS","country_id":48,"country_code":"CO","latitude":"5.63589000","longitude":"-72.19543000"},{"id":"21153","name":"Orocu\u00e9","state_id":2892,"state_code":"CAS","country_id":48,"country_code":"CO","latitude":"4.79035000","longitude":"-71.33917000"},{"id":"21220","name":"Pore","state_id":2892,"state_code":"CAS","country_id":48,"country_code":"CO","latitude":"5.72792000","longitude":"-71.99266000"},{"id":"21279","name":"Recetor","state_id":2892,"state_code":"CAS","country_id":48,"country_code":"CO","latitude":"5.22947000","longitude":"-72.76099000"},{"id":"21310","name":"Sabanalarga","state_id":2892,"state_code":"CAS","country_id":48,"country_code":"CO","latitude":"4.85430000","longitude":"-73.04003000"},{"id":"21381","name":"San Luis de Palenque","state_id":2892,"state_code":"CAS","country_id":48,"country_code":"CO","latitude":"5.42139000","longitude":"-71.73167000"},{"id":"21501","name":"S\u00e1cama","state_id":2892,"state_code":"CAS","country_id":48,"country_code":"CO","latitude":"6.09908000","longitude":"-72.24880000"},{"id":"21516","name":"Tauramena","state_id":2892,"state_code":"CAS","country_id":48,"country_code":"CO","latitude":"5.01789000","longitude":"-72.74675000"},{"id":"21561","name":"T\u00e1mara","state_id":2892,"state_code":"CAS","country_id":48,"country_code":"CO","latitude":"5.82998000","longitude":"-72.16286000"},{"id":"21548","name":"Trinidad","state_id":2892,"state_code":"CAS","country_id":48,"country_code":"CO","latitude":"5.34778000","longitude":"-71.20194000"},{"id":"21607","name":"Villanueva","state_id":2892,"state_code":"CAS","country_id":48,"country_code":"CO","latitude":"5.28333000","longitude":"-71.96667000"},{"id":"21626","name":"Yopal","state_id":2892,"state_code":"CAS","country_id":48,"country_code":"CO","latitude":"5.33775000","longitude":"-72.39586000"}]